[
  {
    "selectValue": "Purified water",
    "inputValue": "15"
  },
  {
    "selectValue": "Acetone",
    "inputValue": "4"
  },
  {
    "selectValue": "Aged Wine",
    "inputValue": "8"
  },
  {
    "selectValue": "Ashika Old Film Canisters",
    "inputValue": "16"
  },
  {
    "selectValue": "Battery",
    "inputValue": "3"
  },
  {
    "selectValue": "Blow Torch",
    "inputValue": "2"
  },
  {
    "selectValue": "Cigar Box",
    "inputValue": "33"
  },
  {
    "selectValue": "Classified Documents",
    "inputValue": "1"
  },
  {
    "selectValue": "Documents",
    "inputValue": "16"
  },
  {
    "selectValue": "Electric Drill",
    "inputValue": "4"
  },
  {
    "selectValue": "Electrical Tape",
    "inputValue": "3"
  },
  {
    "selectValue": "Hydrochloride",
    "inputValue": "3"
  },
  {
    "selectValue": "Japanese/Ashika Liquor",
    "inputValue": "17"
  },
  {
    "selectValue": "Large Medical bag",
    "inputValue": "6"
  },
  {
    "selectValue": "Liquid Nitrogen",
    "inputValue": "10"
  },
  {
    "selectValue": "Screwdriver",
    "inputValue": "5"
  },
  {
    "selectValue": "Wrench",
    "inputValue": "3"
  }
]